pymdownx_superfence_filter_lines/__init__.py
pymdownx_superfence_filter_lines/conftest.py
pymdownx_superfence_filter_lines/py.typed
pymdownx_superfence_filter_lines-0.1.0.dist-info/LICENSE
pymdownx_superfence_filter_lines-0.1.0.dist-info/METADATA
pymdownx_superfence_filter_lines-0.1.0.dist-info/WHEEL
pymdownx_superfence_filter_lines-0.1.0.dist-info/top_level.txt
pymdownx_superfence_filter_lines-0.1.0.dist-info/RECORD
