Metadata-Version: 2.1
Name: pymdownx-superfence-filter-lines
Version: 0.1.0
Summary: A custom superfence for pymdown-extensions that can filters lines and plays nice with MkDocs
Author-email: Frequenz Energy-as-a-Service GmbH <floss@frequenz.com>
License: MIT
Project-URL: Documentation, https://frequenz-floss.github.io/pymdownx-superfence-filter-lines-python/
Project-URL: Changelog, https://github.com/frequenz-floss/pymdownx-superfence-filter-lines-python/releases
Project-URL: Issues, https://github.com/frequenz-floss/pymdownx-superfence-filter-lines-python/issues
Project-URL: Repository, https://github.com/frequenz-floss/pymdownx-superfence-filter-lines-python
Project-URL: Support, https://github.com/frequenz-floss/pymdownx-superfence-filter-lines-python/discussions/categories/support
Keywords: frequenz,python,lib,library,pymdownx-superfence-filter-lines,markdown,filter,mkdocs,python3,mkdocs-material,pymdownx,pymdown-extensions,superfence
Classifier: Development Status :: 3 - Alpha
Classifier: Intended Audience :: Developers
Classifier: License :: OSI Approved :: MIT License
Classifier: Programming Language :: Python :: 3
Classifier: Programming Language :: Python :: 3 :: Only
Classifier: Topic :: Software Development :: Libraries
Classifier: Typing :: Typed
Requires-Python: <4,>=3.11
License-File: LICENSE
Requires-Dist: Markdown <4,>=3.5
Requires-Dist: pymdown-extensions <11,>=10
Provides-Extra: dev
Requires-Dist: pymdownx-superfence-filter-lines[dev-flake8,dev-formatting,dev-mkdocs,dev-mypy,dev-noxfile,dev-pylint,dev-pytest] ; extra == 'dev'
Provides-Extra: dev-flake8
Requires-Dist: flake8 ==6.1.0 ; extra == 'dev-flake8'
Requires-Dist: flake8-docstrings ==1.7.0 ; extra == 'dev-flake8'
Requires-Dist: flake8-pyproject ==1.2.3 ; extra == 'dev-flake8'
Requires-Dist: pydoclint ==0.3.8 ; extra == 'dev-flake8'
Requires-Dist: pydocstyle ==6.3.0 ; extra == 'dev-flake8'
Provides-Extra: dev-formatting
Requires-Dist: black ==23.12.0 ; extra == 'dev-formatting'
Requires-Dist: isort ==5.13.1 ; extra == 'dev-formatting'
Provides-Extra: dev-mkdocs
Requires-Dist: black ==23.12.0 ; extra == 'dev-mkdocs'
Requires-Dist: Markdown ==3.5.1 ; extra == 'dev-mkdocs'
Requires-Dist: mike ==2.0.0 ; extra == 'dev-mkdocs'
Requires-Dist: mkdocs-gen-files ==0.5.0 ; extra == 'dev-mkdocs'
Requires-Dist: mkdocs-literate-nav ==0.6.1 ; extra == 'dev-mkdocs'
Requires-Dist: mkdocs-macros-plugin ==1.0.5 ; extra == 'dev-mkdocs'
Requires-Dist: mkdocs-material ==9.5.2 ; extra == 'dev-mkdocs'
Requires-Dist: mkdocstrings[python] ==0.24.0 ; extra == 'dev-mkdocs'
Requires-Dist: frequenz-repo-config[lib] ==0.7.5 ; extra == 'dev-mkdocs'
Provides-Extra: dev-mypy
Requires-Dist: mypy ==1.7.1 ; extra == 'dev-mypy'
Requires-Dist: types-Markdown ==3.5.0.3 ; extra == 'dev-mypy'
Requires-Dist: pymdownx-superfence-filter-lines[dev-mkdocs,dev-noxfile,dev-pytest] ; extra == 'dev-mypy'
Provides-Extra: dev-noxfile
Requires-Dist: nox ==2023.4.22 ; extra == 'dev-noxfile'
Requires-Dist: frequenz-repo-config[lib] ==0.7.5 ; extra == 'dev-noxfile'
Provides-Extra: dev-pylint
Requires-Dist: pylint ==3.0.3 ; extra == 'dev-pylint'
Requires-Dist: pymdownx-superfence-filter-lines[dev-mkdocs,dev-noxfile,dev-pytest] ; extra == 'dev-pylint'
Provides-Extra: dev-pytest
Requires-Dist: pytest ==7.4.3 ; extra == 'dev-pytest'
Requires-Dist: frequenz-repo-config[extra-lint-examples] ==0.7.5 ; extra == 'dev-pytest'
Requires-Dist: pytest-mock ==3.12.0 ; extra == 'dev-pytest'
Requires-Dist: pytest-asyncio ==0.23.2 ; extra == 'dev-pytest'
Requires-Dist: async-solipsism ==0.5 ; extra == 'dev-pytest'
